flask_limit/__init__.py
flask_limit/rate_limit.py
Flask_Limit-1.0.3.dist-info/AUTHORS
Flask_Limit-1.0.3.dist-info/LICENSE
Flask_Limit-1.0.3.dist-info/METADATA
Flask_Limit-1.0.3.dist-info/WHEEL
Flask_Limit-1.0.3.dist-info/top_level.txt
Flask_Limit-1.0.3.dist-info/RECORD
