Metadata-Version: 2.1
Name: Flask-Limit
Version: 1.0.3
Summary: An extension that provides rate limiting for Flask routes.
Home-page: https://github.com/tabotkevin/flask_limit
Author: Tabot Kevin
Author-email: tabot.kevin@gmail.com
License: MIT
Platform: any
Classifier: Environment :: Web Environment
Classifier: Intended Audience :: Developers
Classifier: License :: OSI Approved :: MIT License
Classifier: Operating System :: OS Independent
Classifier: Programming Language :: Python
Classifier: Programming Language :: Python :: 2
Classifier: Programming Language :: Python :: 3
Classifier: Topic :: Internet :: WWW/HTTP :: Dynamic Content
Classifier: Topic :: Software Development :: Libraries :: Python Modules
License-File: LICENSE
License-File: AUTHORS
Requires-Dist: Flask
